nado_protocol/__init__.py
nado_protocol/client/__init__.py
nado_protocol/client/apis/__init__.py
nado_protocol/client/apis/base.py
nado_protocol/client/apis/market/__init__.py
nado_protocol/client/apis/market/execute.py
nado_protocol/client/apis/market/query.py
nado_protocol/client/apis/perp/__init__.py
nado_protocol/client/apis/perp/query.py
nado_protocol/client/apis/rewards/__init__.py
nado_protocol/client/apis/rewards/execute.py
nado_protocol/client/apis/rewards/query.py
nado_protocol/client/apis/spot/__init__.py
nado_protocol/client/apis/spot/base.py
nado_protocol/client/apis/spot/execute.py
nado_protocol/client/apis/spot/query.py
nado_protocol/client/apis/subaccount/__init__.py
nado_protocol/client/apis/subaccount/execute.py
nado_protocol/client/apis/subaccount/query.py
nado_protocol/client/context.py
nado_protocol/contracts/__init__.py
nado_protocol/contracts/abis/Endpoint.json
nado_protocol/contracts/abis/FQuerier.json
nado_protocol/contracts/abis/IAirdrop.json
nado_protocol/contracts/abis/IClearinghouse.json
nado_protocol/contracts/abis/IEndpoint.json
nado_protocol/contracts/abis/IFoundationRewardsAirdrop.json
nado_protocol/contracts/abis/IPerpEngine.json
nado_protocol/contracts/abis/IProductEngine.json
nado_protocol/contracts/abis/ISpotEngine.json
nado_protocol/contracts/abis/IStaking.json
nado_protocol/contracts/abis/MockERC20.json
nado_protocol/contracts/deployments/deployment.mainnet.json
nado_protocol/contracts/deployments/deployment.testing.json
nado_protocol/contracts/deployments/deployment.testnet.json
nado_protocol/contracts/eip712/__init__.py
nado_protocol/contracts/eip712/domain.py
nado_protocol/contracts/eip712/sign.py
nado_protocol/contracts/eip712/types.py
nado_protocol/contracts/loader.py
nado_protocol/contracts/types.py
nado_protocol/engine_client/__init__.py
nado_protocol/engine_client/execute.py
nado_protocol/engine_client/query.py
nado_protocol/engine_client/types/__init__.py
nado_protocol/engine_client/types/execute.py
nado_protocol-0.3.2.dist-info/METADATA
nado_protocol-0.3.2.dist-info/WHEEL
nado_protocol-0.3.2.dist-info/entry_points.txt
nado_protocol-0.3.2.dist-info/RECORD
