Metadata-Version: 2.4
Name: nado-protocol
Version: 0.3.2
Summary: Nado Protocol SDK
Keywords: nado protocol,nado sdk,nado protocol api
Author: Jeury Mejia
Author-email: jeury@inkfnd.com
Maintainer: Frank Jia
Maintainer-email: frank@inkfnd.com
Requires-Python: >=3.9,<4.0
Classifier: Programming Language :: Python :: 3
Classifier: Programming Language :: Python :: 3.9
Classifier: Programming Language :: Python :: 3.10
Classifier: Programming Language :: Python :: 3.11
Classifier: Programming Language :: Python :: 3.12
Classifier: Programming Language :: Python :: 3.13
Classifier: Programming Language :: Python :: 3.14
Requires-Dist: eth-account (>=0.8.0,<0.9.0)
Requires-Dist: pydantic (>=1.10.7,<2.0.0)
Requires-Dist: web3 (>=6.4.0,<7.0.0)
Project-URL: Documentation, https://nadohq.github.io/nado-python-sdk/
Project-URL: Homepage, https://nado.xyz
